LICENSE
README.md
setup.cfg
setup.py
ph4_upsmonit.egg-info/PKG-INFO
ph4_upsmonit.egg-info/SOURCES.txt
ph4_upsmonit.egg-info/dependency_links.txt
ph4_upsmonit.egg-info/entry_points.txt
ph4_upsmonit.egg-info/requires.txt
ph4_upsmonit.egg-info/top_level.txt
ph4upsmonit/__init__.py
ph4upsmonit/test.py
ph4upsmonit/ups.py